{
    "Artical": "　　新浪体育讯　北京时间12月7日，2013赛季中国足协杯决赛第二回合的比赛在广州打响，广州恒大坐镇主场天河体育场迎战贵州人和，最终贵州总比分3-2战胜恒大，获得足协杯冠军。然而在贵州队夺冠后庆祝的场面中却无法看到穆斯利的身影，由于在比赛中被恒大队秦升踢到了头部而流血不止，穆斯利一度被送上了救护车。　　下半场60分钟，秦升顶替冯潇霆替补出场，登场后秦升动作凶狠，几次通过犯规阻止贵州人和的进攻。当比赛进行到底84分钟时，孙继海大脚开球门球到前场，皮球来到穆斯利面前，身后的秦升看到皮球从空中落下时，半转身抬起右脚够球，却狠狠的踢在了穆斯利的脸上，穆斯利当场倒地，鼻子流血不止，被担架抬到场下，队医在对他进行了简单的救治后，穆斯利被送上了救护车。　　据贵州人和队员张成林赛后透露，穆斯利的鼻梁骨骨折成四节。　　据悉，在医院经过紧急处理后，铁汉火速返回庆功现场，不过因为碎骨太多，中国医生不敢进行手术，明早他将返回塞尔维亚进行手术。　　(旺旺) , ",
    "ID": "6-12-6922131", 
    "Keyword": "", 
    "Reply": "26772", 
    "Show": "4245", 
    "Source": "sina", 
    "Time": "2013年12月07日22:00", 
    "Title": "秦升爆头踢碎穆斯利鼻梁!碎骨多医生不敢手术(图)", 
    "Total": "31770", 
    "URL": "http://sports.sina.com.cn/j/2013-12-07/18206922131.shtml"
}
